[
  [
    {
      "user_id": 67980574,
      "first_name": "ea esse",
      "last_name": "fugiat dolore officia ut",
      "email": "mRJoyf@AyEGCbYcGsbKuKbJKqdGjJUHduyl.iiu"
    },
    {
      "user_id": 2867246,
      "first_name": "veniam minim voluptate Duis",
      "last_name": "laboris sunt sint",
      "email": "plu8@vhTGleQKggUYVnLQTpMgHw.sjhe"
    },
    {
      "user_id": -1357754,
      "first_name": "officia magna",
      "last_name": "Lorem ut sit ex mollit",
      "email": "9mImkPKS6tcMZDV@KugssvDSFPu.iwd"
    },
    {
      "user_id": -50804665,
      "first_name": "do",
      "last_name": "esse",
      "email": "n8kULBb0QD@CbN.hjd"
    },
    {
      "user_id": 48692074,
      "first_name": "ut id eiusmod",
      "last_name": "eiusmod non dolore irure ad",
      "email": "bZKDIQAjUCS2W@hFtrErSnOhZYqQDAuDpRyUSxcICRb.iggd"
    }
  ],
  [
    {
      "user_id": 96703590,
      "first_name": "exercitation cillum nostrud deserunt",
      "last_name": "sit est labore nostrud irure",
      "email": "aZHbmvOiTMYk@yJsuyLcYspmTPDvvlWuZmZPogG.hl"
    },
    {
      "user_id": 65771264,
      "first_name": "ullamco commodo Lorem proident",
      "last_name": "et enim sunt eiusmod nulla",
      "email": "ogxGCahNaR-Eh5d@KWGDzOvv.oyu"
    },
    {
      "user_id": -49244753,
      "first_name": "nulla laboris esse nostrud in",
      "last_name": "ad cupidatat Ut velit eu",
      "email": "Efofv7vZ@V.ss"
    },
    {
      "user_id": 61766837,
      "first_name": "adipisicing",
      "last_name": "ex cupidatat",
      "email": "uXWwSCWQLf42kdu@NkWEHLJKjXHeePCAeyPhstEHNYDeqP.toot"
    },
    {
      "user_id": 72998814,
      "first_name": "non officia minim commodo deserunt",
      "last_name": "est",
      "email": "yeP4fw@gAYgptuLuITPWtcThLtAXVCq.eri"
    }
  ]
]